Flask_ClickHouse-1.0.1.dist-info/DESCRIPTION.rst
Flask_ClickHouse-1.0.1.dist-info/METADATA
Flask_ClickHouse-1.0.1.dist-info/RECORD
Flask_ClickHouse-1.0.1.dist-info/WHEEL
Flask_ClickHouse-1.0.1.dist-info/metadata.json
Flask_ClickHouse-1.0.1.dist-info/top_level.txt
flask_clickhouse/__init__.py
