Metadata-Version: 2.0
Name: Flask-ClickHouse
Version: 1.0.1
Summary: ClickHouse support for Flask applications
Home-page: https://github.com/aolefira/flask-clickhouse
Author: Andrew Olefira
Author-email: andrew.olefira@gmail.com
License: GNU General Public License v3.0
Platform: UNKNOWN
Classifier: Environment :: Web Environment
Classifier: Intended Audience :: Developers
Classifier: License :: OSI Approved :: GNU General Public License v3 (GPLv3)
Classifier: Operating System :: OS Independent
Classifier: Programming Language :: Python
Classifier: Programming Language :: Python :: 3
Classifier: Programming Language :: Python :: 3.2
Classifier: Programming Language :: Python :: 3.3
Classifier: Programming Language :: Python :: 3.4
Classifier: Programming Language :: Python :: 3.5
Classifier: Programming Language :: Python :: 3.6
Classifier: Topic :: Internet :: WWW/HTTP :: Dynamic Content
Classifier: Topic :: Software Development :: Libraries :: Python Modules
Requires-Dist: clickhouse-driver (>=0.0.9)
